{
  "users": [
    {
      "id": "ccbff41b-ad19-41bb-849b-7bccbb5b3144",
      "userName": "Neha",
      "email": "neha@gmail.com",
      "password": "123456",
      "confirmPassword": "123456",
      "mobile": "8881946755",
      "gender": "female",
      "profileImage": "./male_avatar.png",
      "board": []
    },
    {
      "id": "bacc4a0d-a6b7-41f0-9aac-819b7257ce47",
      "userName": "shubham",
      "email": "tshubhamucem@gmail.com",
      "password": "@tshubham1",
      "confirmPassword": "@tshubham1",
      "mobile": "8881946755",
      "gender": "male",
      "profileImage": "./male_avatar.png",
      "board": []
    }
  ]
}
